README.rst
setup.py
cookpy/__init__.py
cookpy/const.py
cookpy/cook.py
cookpy/exceptions.py
cookpy/parser.py
cookpy/targets.py
cookpy/utils.py
cookpy.egg-info/PKG-INFO
cookpy.egg-info/SOURCES.txt
cookpy.egg-info/dependency_links.txt
cookpy.egg-info/top_level.txt