Metadata-Version: 1.1
Name: cookpy
Version: 0.0.1
Summary: A cross-platform, free and open-source build system
Home-page: https://github.com/cookpy/cookpy
Author: koehlja
Author-email: UNKNOWN
License: UNKNOWN
Keywords: cookpy,cook,py,build,system,tools
Platform: UNKNOWN
Classifier: Development Status :: 2 - Pre-Alpha
Classifier: Intended Audience :: Developers
Classifier: Programming Language :: Python
Classifier: Programming Language :: Python :: 3
Classifier: Programming Language :: Python :: 3.0
Classifier: Programming Language :: Python :: 3.1
Classifier: Programming Language :: Python :: 3.2
Classifier: Programming Language :: Python :: 3.3
Classifier: Programming Language :: Python :: 3.4
Classifier: Programming Language :: Python :: 3.5
Classifier: Programming Language :: Python :: 3 :: Only
Classifier: Topic :: Software Development
Classifier: Topic :: Software Development :: Build Tools
